mensajes/__init__.py
mensajes/adios/__init__.py
mensajes/adios/despedidas.py
mensajes/hola1/__init__.py
mensajes/hola1/saludos.py
tests/__init__.py
tests/test_hola.py
Mensajes_Mand44-6.0.dist-info/LICENSE
Mensajes_Mand44-6.0.dist-info/METADATA
Mensajes_Mand44-6.0.dist-info/WHEEL
Mensajes_Mand44-6.0.dist-info/top_level.txt
Mensajes_Mand44-6.0.dist-info/RECORD
